replay_cache/__init__.py
replay_cache-0.2.0.dist-info/LICENSE
replay_cache-0.2.0.dist-info/METADATA
replay_cache-0.2.0.dist-info/WHEEL
replay_cache-0.2.0.dist-info/RECORD
