Metadata-Version: 2.1
Name: replay-cache
Version: 0.2.0
Summary: Replaying cache for LangChain
Author: Ada Bohm
Author-email: ada@kreatrix.org
Requires-Python: >=3.10,<4.0
Classifier: Programming Language :: Python :: 3
Classifier: Programming Language :: Python :: 3.10
Classifier: Programming Language :: Python :: 3.11
Requires-Dist: langchain-core (>=0.1.30,<0.2.0)
